paola/__init__.py
paola-0.0.1.dist-info/licenses/LICENSE
paola-0.0.1.dist-info/METADATA
paola-0.0.1.dist-info/WHEEL
paola-0.0.1.dist-info/top_level.txt
paola-0.0.1.dist-info/RECORD
